odoo/addons/sale_mrp_bom/README.rst
odoo/addons/sale_mrp_bom/__init__.py
odoo/addons/sale_mrp_bom/__manifest__.py
odoo/addons/sale_mrp_bom/i18n/ca.po
odoo/addons/sale_mrp_bom/i18n/es.po
odoo/addons/sale_mrp_bom/i18n/sale_mrp_bom.pot
odoo/addons/sale_mrp_bom/models/__init__.py
odoo/addons/sale_mrp_bom/models/sale_order_line.py
odoo/addons/sale_mrp_bom/models/stock_move.py
odoo/addons/sale_mrp_bom/readme/CONFIGURE.rst
odoo/addons/sale_mrp_bom/readme/CONTRIBUTORS.rst
odoo/addons/sale_mrp_bom/readme/DESCRIPTION.rst
odoo/addons/sale_mrp_bom/readme/INSTALL.rst
odoo/addons/sale_mrp_bom/readme/ROADMAP.rst
odoo/addons/sale_mrp_bom/readme/USAGE.rst
odoo/addons/sale_mrp_bom/security/security.xml
odoo/addons/sale_mrp_bom/static/description/icon.png
odoo/addons/sale_mrp_bom/static/description/index.html
odoo/addons/sale_mrp_bom/static/description/manufacturing_order_1.png
odoo/addons/sale_mrp_bom/static/description/sale_order_1.png
odoo/addons/sale_mrp_bom/tests/__init__.py
odoo/addons/sale_mrp_bom/tests/test_sale_mrp_bom.py
odoo/addons/sale_mrp_bom/views/sale_order.xml
odoo/addons/sale_mrp_bom/views/sale_order_line.xml
odoo12_addon_sale_mrp_bom-12.0.1.0.1.dist-info/METADATA
odoo12_addon_sale_mrp_bom-12.0.1.0.1.dist-info/WHEEL
odoo12_addon_sale_mrp_bom-12.0.1.0.1.dist-info/top_level.txt
odoo12_addon_sale_mrp_bom-12.0.1.0.1.dist-info/RECORD
